{
    "objects": [
        {
            "data": [
                844,
                124,
                30,
                40
            ],
            "tags": [
                "h",
                "not_impact"
            ],
            "type": "rect"
        },
        {
            "data": [
                852,
                215,
                33,
                34
            ],
            "tags": [
                "h",
                "not_impact"
            ],
            "type": "rect"
        },
        {
            "data": [
                751,
                422,
                27,
                35
            ],
            "tags": [
                "h",
                "not_impact"
            ],
            "type": "rect"
        },
        {
            "data": [
                524,
                380,
                34,
                36
            ],
            "tags": [
                "h",
                "not_impact"
            ],
            "type": "rect"
        },
        {
            "data": [
                855,
                254,
                37,
                38
            ],
            "tags": [
                "h",
                "not_impact"
            ],
            "type": "rect"
        },
        {
            "data": [
                793,
                413,
                33,
                32
            ],
            "tags": [
                "h",
                "not_impact"
            ],
            "type": "rect"
        },
        {
            "data": [
                677,
                387,
                34,
                33
            ],
            "tags": [
                "h",
                "not_impact"
            ],
            "type": "rect"
        },
        {
            "data": [
                765,
                248,
                30,
                42
            ],
            "tags": [
                "h",
                "not_impact"
            ],
            "type": "rect"
        },
        {
            "data": [
                724,
                339,
                33,
                43
            ],
            "tags": [
                "h",
                "not_impact"
            ],
            "type": "rect"
        },
        {
            "data": [
                673,
                182,
                36,
                41
            ],
            "tags": [
                "h",
                "not_impact"
            ],
            "type": "rect"
        },
        {
            "data": [
                1080,
                186,
                32,
                37
            ],
            "tags": [
                "h",
                "not_impact"
            ],
            "type": "rect"
        },
        {
            "data": [
                1110,
                498,
                33,
                34
            ],
            "tags": [
                "h",
                "not_impact"
            ],
            "type": "rect"
        },
        {
            "data": [
                841,
                377,
                32,
                33
            ],
            "tags": [
                "h",
                "not_impact"
            ],
            "type": "rect"
        },
        {
            "data": [
                974,
                498,
                37,
                34
            ],
            "tags": [
                "h",
                "not_impact"
            ],
            "type": "rect"
        },
        {
            "data": [
                924,
                272,
                38,
                35
            ],
            "tags": [
                "h",
                "not_impact"
            ],
            "type": "rect"
        },
        {
            "data": [
                1072,
                267,
                30,
                40
            ],
            "tags": [
                "h",
                "not_impact"
            ],
            "type": "rect"
        },
        {
            "data": [
                730,
                383,
                21,
                24
            ],
            "tags": [
                "h",
                "not_impact"
            ],
            "type": "rect"
        },
        {
            "data": [
                743,
                112,
                29,
                42
            ],
            "tags": [
                "h",
                "not_impact"
            ],
            "type": "rect"
        }
    ]
}