{
    "objects": [
        {
            "data": [
                103,
                174,
                54,
                60
            ],
            "tags": [
                "h",
                "not_impact"
            ],
            "type": "rect"
        },
        {
            "data": [
                165,
                93,
                53,
                59
            ],
            "tags": [
                "h",
                "not_impact"
            ],
            "type": "rect"
        },
        {
            "data": [
                537,
                270,
                55,
                67
            ],
            "tags": [
                "h",
                "not_impact"
            ],
            "type": "rect"
        },
        {
            "data": [
                1256,
                143,
                23,
                50
            ],
            "tags": [
                "h",
                "not_impact"
            ],
            "type": "rect"
        },
        {
            "data": [
                636,
                102,
                50,
                63
            ],
            "tags": [
                "h",
                "not_impact"
            ],
            "type": "rect"
        },
        {
            "data": [
                782,
                297,
                53,
                52
            ],
            "tags": [
                "h",
                "not_impact"
            ],
            "type": "rect"
        },
        {
            "data": [
                407,
                272,
                49,
                52
            ],
            "tags": [
                "h",
                "not_impact"
            ],
            "type": "rect"
        },
        {
            "data": [
                500,
                274,
                39,
                31
            ],
            "tags": [
                "h",
                "not_impact"
            ],
            "type": "rect"
        },
        {
            "data": [
                653,
                190,
                49,
                68
            ],
            "tags": [
                "h",
                "not_impact"
            ],
            "type": "rect"
        },
        {
            "data": [
                454,
                272,
                55,
                46
            ],
            "tags": [
                "h",
                "not_impact"
            ],
            "type": "rect"
        },
        {
            "data": [
                211,
                161,
                52,
                67
            ],
            "tags": [
                "h",
                "not_impact"
            ],
            "type": "rect"
        },
        {
            "data": [
                23,
                119,
                59,
                59
            ],
            "tags": [
                "h",
                "not_impact"
            ],
            "type": "rect"
        },
        {
            "data": [
                923,
                100,
                54,
                62
            ],
            "tags": [
                "h",
                "not_impact"
            ],
            "type": "rect"
        }
    ]
}