{
    "objects": [
        {
            "data": [
                494,
                299,
                14,
                16
            ],
            "tags": [
                "h",
                "Helmet-Partial"
            ],
            "type": "rect"
        },
        {
            "data": [
                738,
                194,
                20,
                17
            ],
            "tags": [
                "h",
                "Helmet"
            ],
            "type": "rect"
        },
        {
            "data": [
                786,
                363,
                30,
                21
            ],
            "tags": [
                "h",
                "Helmet"
            ],
            "type": "rect"
        },
        {
            "data": [
                769,
                447,
                24,
                20
            ],
            "tags": [
                "h",
                "Helmet"
            ],
            "type": "rect"
        },
        {
            "data": [
                568,
                696,
                27,
                22
            ],
            "tags": [
                "h",
                "Helmet"
            ],
            "type": "rect"
        },
        {
            "data": [
                503,
                280,
                20,
                25
            ],
            "tags": [
                "h",
                "Helmet"
            ],
            "type": "rect"
        },
        {
            "data": [
                639,
                165,
                20,
                28
            ],
            "tags": [
                "h",
                "Helmet"
            ],
            "type": "rect"
        },
        {
            "data": [
                591,
                191,
                20,
                26
            ],
            "tags": [
                "h",
                "Helmet"
            ],
            "type": "rect"
        },
        {
            "data": [
                498,
                239,
                21,
                26
            ],
            "tags": [
                "h",
                "Helmet"
            ],
            "type": "rect"
        },
        {
            "data": [
                436,
                226,
                25,
                26
            ],
            "tags": [
                "h",
                "Helmet"
            ],
            "type": "rect"
        },
        {
            "data": [
                751,
                210,
                16,
                12
            ],
            "tags": [
                "h",
                "Helmet-Partial"
            ],
            "type": "rect"
        },
        {
            "data": [
                261,
                503,
                22,
                22
            ],
            "tags": [
                "h",
                "Helmet"
            ],
            "type": "rect"
        },
        {
            "data": [
                794,
                201,
                23,
                21
            ],
            "tags": [
                "h",
                "Helmet"
            ],
            "type": "rect"
        },
        {
            "data": [
                608,
                219,
                21,
                15
            ],
            "tags": [
                "h",
                "Helmet-Blurred"
            ],
            "type": "rect"
        },
        {
            "data": [
                242,
                504,
                28,
                29
            ],
            "tags": [
                "h",
                "Helmet"
            ],
            "type": "rect"
        },
        {
            "data": [
                3,
                464,
                26,
                20
            ],
            "tags": [
                "h",
                "Helmet"
            ],
            "type": "rect"
        }
    ]
}