{
    "objects": [
        {
            "data": [
                388,
                328,
                21,
                17
            ],
            "tags": [
                "h",
                "Helmet"
            ],
            "type": "rect"
        },
        {
            "data": [
                486,
                551,
                20,
                21
            ],
            "tags": [
                "h",
                "Helmet"
            ],
            "type": "rect"
        },
        {
            "data": [
                537,
                556,
                22,
                22
            ],
            "tags": [
                "h",
                "Helmet"
            ],
            "type": "rect"
        },
        {
            "data": [
                494,
                421,
                20,
                16
            ],
            "tags": [
                "h",
                "Helmet"
            ],
            "type": "rect"
        },
        {
            "data": [
                193,
                333,
                18,
                17
            ],
            "tags": [
                "h",
                "Helmet"
            ],
            "type": "rect"
        },
        {
            "data": [
                313,
                334,
                18,
                17
            ],
            "tags": [
                "h",
                "Helmet"
            ],
            "type": "rect"
        },
        {
            "data": [
                635,
                372,
                21,
                16
            ],
            "tags": [
                "h",
                "Helmet"
            ],
            "type": "rect"
        },
        {
            "data": [
                513,
                352,
                17,
                17
            ],
            "tags": [
                "h",
                "Helmet-Difficult"
            ],
            "type": "rect"
        },
        {
            "data": [
                941,
                439,
                20,
                22
            ],
            "tags": [
                "h",
                "Helmet"
            ],
            "type": "rect"
        },
        {
            "data": [
                959,
                252,
                16,
                20
            ],
            "tags": [
                "h",
                "Helmet"
            ],
            "type": "rect"
        },
        {
            "data": [
                692,
                261,
                17,
                18
            ],
            "tags": [
                "h",
                "Helmet"
            ],
            "type": "rect"
        },
        {
            "data": [
                705,
                308,
                16,
                15
            ],
            "tags": [
                "h",
                "Helmet"
            ],
            "type": "rect"
        },
        {
            "data": [
                531,
                351,
                19,
                19
            ],
            "tags": [
                "h",
                "Helmet"
            ],
            "type": "rect"
        },
        {
            "data": [
                532,
                144,
                15,
                18
            ],
            "tags": [
                "h",
                "Helmet"
            ],
            "type": "rect"
        },
        {
            "data": [
                582,
                142,
                19,
                20
            ],
            "tags": [
                "h",
                "Helmet"
            ],
            "type": "rect"
        },
        {
            "data": [
                469,
                250,
                17,
                16
            ],
            "tags": [
                "h",
                "Helmet"
            ],
            "type": "rect"
        },
        {
            "data": [
                484,
                267,
                15,
                15
            ],
            "tags": [
                "h",
                "Helmet"
            ],
            "type": "rect"
        },
        {
            "data": [
                527,
                302,
                15,
                19
            ],
            "tags": [
                "h",
                "Helmet"
            ],
            "type": "rect"
        },
        {
            "data": [
                539,
                307,
                19,
                16
            ],
            "tags": [
                "h",
                "Helmet"
            ],
            "type": "rect"
        },
        {
            "data": [
                519,
                324,
                14,
                13
            ],
            "tags": [
                "h",
                "Helmet-Difficult"
            ],
            "type": "rect"
        },
        {
            "data": [
                522,
                260,
                17,
                21
            ],
            "tags": [
                "h",
                "Helmet"
            ],
            "type": "rect"
        },
        {
            "data": [
                491,
                381,
                15,
                18
            ],
            "tags": [
                "h",
                "Helmet"
            ],
            "type": "rect"
        }
    ]
}