{
    "objects": [
        {
            "data": [
                360,
                311,
                21,
                21
            ],
            "tags": [
                "h",
                "not_impact"
            ],
            "type": "rect"
        },
        {
            "data": [
                559,
                242,
                21,
                17
            ],
            "tags": [
                "h",
                "not_impact"
            ],
            "type": "rect"
        },
        {
            "data": [
                701,
                300,
                24,
                24
            ],
            "tags": [
                "h",
                "not_impact"
            ],
            "type": "rect"
        },
        {
            "data": [
                528,
                280,
                21,
                29
            ],
            "tags": [
                "h",
                "not_impact"
            ],
            "type": "rect"
        },
        {
            "data": [
                245,
                369,
                24,
                29
            ],
            "tags": [
                "h",
                "not_impact"
            ],
            "type": "rect"
        },
        {
            "data": [
                206,
                90,
                22,
                28
            ],
            "tags": [
                "h",
                "not_impact"
            ],
            "type": "rect"
        },
        {
            "data": [
                910,
                265,
                24,
                18
            ],
            "tags": [
                "h",
                "not_impact"
            ],
            "type": "rect"
        },
        {
            "data": [
                653,
                238,
                24,
                27
            ],
            "tags": [
                "h",
                "not_impact"
            ],
            "type": "rect"
        },
        {
            "data": [
                779,
                245,
                27,
                24
            ],
            "tags": [
                "h",
                "not_impact"
            ],
            "type": "rect"
        },
        {
            "data": [
                249,
                600,
                25,
                23
            ],
            "tags": [
                "h",
                "not_impact"
            ],
            "type": "rect"
        },
        {
            "data": [
                861,
                224,
                26,
                26
            ],
            "tags": [
                "h",
                "not_impact"
            ],
            "type": "rect"
        },
        {
            "data": [
                369,
                288,
                22,
                25
            ],
            "tags": [
                "h",
                "not_impact"
            ],
            "type": "rect"
        },
        {
            "data": [
                549,
                275,
                27,
                23
            ],
            "tags": [
                "h",
                "not_impact"
            ],
            "type": "rect"
        },
        {
            "data": [
                558,
                254,
                23,
                23
            ],
            "tags": [
                "h",
                "not_impact"
            ],
            "type": "rect"
        },
        {
            "data": [
                935,
                264,
                25,
                24
            ],
            "tags": [
                "h",
                "not_impact"
            ],
            "type": "rect"
        },
        {
            "data": [
                823,
                302,
                23,
                23
            ],
            "tags": [
                "h",
                "not_impact"
            ],
            "type": "rect"
        },
        {
            "data": [
                855,
                247,
                20,
                22
            ],
            "tags": [
                "h",
                "not_impact"
            ],
            "type": "rect"
        },
        {
            "data": [
                1036,
                284,
                20,
                19
            ],
            "tags": [
                "h",
                "not_impact"
            ],
            "type": "rect"
        },
        {
            "data": [
                738,
                253,
                24,
                25
            ],
            "tags": [
                "h",
                "not_impact"
            ],
            "type": "rect"
        }
    ]
}