{
    "objects": [
        {
            "data": [
                767,
                467,
                26,
                27
            ],
            "tags": [
                "h",
                "not_impact"
            ],
            "type": "rect"
        },
        {
            "data": [
                670,
                204,
                20,
                30
            ],
            "tags": [
                "h",
                "not_impact"
            ],
            "type": "rect"
        },
        {
            "data": [
                346,
                327,
                28,
                27
            ],
            "tags": [
                "h",
                "not_impact"
            ],
            "type": "rect"
        },
        {
            "data": [
                423,
                406,
                28,
                28
            ],
            "tags": [
                "h",
                "not_impact"
            ],
            "type": "rect"
        },
        {
            "data": [
                781,
                259,
                29,
                28
            ],
            "tags": [
                "h",
                "not_impact"
            ],
            "type": "rect"
        },
        {
            "data": [
                716,
                314,
                23,
                23
            ],
            "tags": [
                "h",
                "not_impact"
            ],
            "type": "rect"
        },
        {
            "data": [
                107,
                264,
                31,
                27
            ],
            "tags": [
                "h",
                "not_impact"
            ],
            "type": "rect"
        },
        {
            "data": [
                338,
                313,
                30,
                24
            ],
            "tags": [
                "h",
                "not_impact"
            ],
            "type": "rect"
        },
        {
            "data": [
                651,
                443,
                30,
                27
            ],
            "tags": [
                "h",
                "not_impact"
            ],
            "type": "rect"
        },
        {
            "data": [
                687,
                181,
                22,
                28
            ],
            "tags": [
                "h",
                "not_impact"
            ],
            "type": "rect"
        },
        {
            "data": [
                453,
                262,
                28,
                29
            ],
            "tags": [
                "h",
                "not_impact"
            ],
            "type": "rect"
        },
        {
            "data": [
                670,
                256,
                21,
                33
            ],
            "tags": [
                "h",
                "not_impact"
            ],
            "type": "rect"
        },
        {
            "data": [
                1171,
                456,
                33,
                31
            ],
            "tags": [
                "h",
                "not_impact"
            ],
            "type": "rect"
        },
        {
            "data": [
                772,
                300,
                29,
                30
            ],
            "tags": [
                "h",
                "not_impact"
            ],
            "type": "rect"
        },
        {
            "data": [
                1232,
                382,
                27,
                26
            ],
            "tags": [
                "h",
                "not_impact"
            ],
            "type": "rect"
        }
    ]
}