{
    "objects": [
        {
            "data": [
                745,
                359,
                19,
                27
            ],
            "tags": [
                "h",
                "not_impact"
            ],
            "type": "rect"
        },
        {
            "data": [
                297,
                374,
                21,
                19
            ],
            "tags": [
                "h",
                "not_impact"
            ],
            "type": "rect"
        },
        {
            "data": [
                1158,
                473,
                24,
                20
            ],
            "tags": [
                "h",
                "not_impact"
            ],
            "type": "rect"
        },
        {
            "data": [
                593,
                377,
                18,
                10
            ],
            "tags": [
                "h",
                "not_impact"
            ],
            "type": "rect"
        },
        {
            "data": [
                140,
                343,
                22,
                19
            ],
            "tags": [
                "h",
                "not_impact"
            ],
            "type": "rect"
        },
        {
            "data": [
                351,
                492,
                26,
                20
            ],
            "tags": [
                "h",
                "not_impact"
            ],
            "type": "rect"
        },
        {
            "data": [
                1095,
                377,
                23,
                17
            ],
            "tags": [
                "h",
                "not_impact"
            ],
            "type": "rect"
        },
        {
            "data": [
                767,
                371,
                23,
                18
            ],
            "tags": [
                "h",
                "not_impact"
            ],
            "type": "rect"
        },
        {
            "data": [
                708,
                217,
                20,
                28
            ],
            "tags": [
                "h",
                "not_impact"
            ],
            "type": "rect"
        },
        {
            "data": [
                622,
                348,
                20,
                28
            ],
            "tags": [
                "h",
                "not_impact"
            ],
            "type": "rect"
        },
        {
            "data": [
                518,
                337,
                21,
                29
            ],
            "tags": [
                "h",
                "not_impact"
            ],
            "type": "rect"
        },
        {
            "data": [
                951,
                430,
                8,
                9
            ],
            "tags": [
                "h",
                "not_impact"
            ],
            "type": "rect"
        },
        {
            "data": [
                156,
                310,
                21,
                26
            ],
            "tags": [
                "h",
                "not_impact"
            ],
            "type": "rect"
        },
        {
            "data": [
                842,
                346,
                23,
                31
            ],
            "tags": [
                "h",
                "not_impact"
            ],
            "type": "rect"
        },
        {
            "data": [
                409,
                350,
                20,
                27
            ],
            "tags": [
                "h",
                "not_impact"
            ],
            "type": "rect"
        },
        {
            "data": [
                734,
                313,
                20,
                28
            ],
            "tags": [
                "h",
                "not_impact"
            ],
            "type": "rect"
        },
        {
            "data": [
                696,
                414,
                23,
                19
            ],
            "tags": [
                "h",
                "not_impact"
            ],
            "type": "rect"
        },
        {
            "data": [
                460,
                395,
                25,
                16
            ],
            "tags": [
                "h",
                "not_impact"
            ],
            "type": "rect"
        },
        {
            "data": [
                322,
                341,
                21,
                28
            ],
            "tags": [
                "h",
                "not_impact"
            ],
            "type": "rect"
        }
    ]
}